{
  "batchId": "batch-008",
  "problems": [
    {
      "id": "0141",
      "slug": "linked-list-cycle",
      "title": "Linked List Cycle",
      "difficulty": "EASY",
      "tags": [
        "hash-table",
        "linked-list",
        "two-pointers"
      ],
      "classHeavy": false,
      "oracleTier": "bank",
      "oracleFnName": "hasCycle"
    },
    {
      "id": "0142",
      "slug": "linked-list-cycle-ii",
      "title": "Linked List Cycle II",
      "difficulty": "MEDIUM",
      "tags": [
        "hash-table",
        "linked-list",
        "two-pointers"
      ],
      "classHeavy": false,
      "oracleTier": "bank",
      "oracleFnName": "detectCycle"
    },
    {
      "id": "0143",
      "slug": "reorder-list",
      "title": "Reorder List",
      "difficulty": "MEDIUM",
      "tags": [
        "linked-list",
        "two-pointers",
        "stack",
        "recursion"
      ],
      "classHeavy": false,
      "oracleTier": "bank",
      "oracleFnName": "reorderList"
    },
    {
      "id": "0144",
      "slug": "binary-tree-preorder-traversal",
      "title": "Binary Tree Preorder Traversal",
      "difficulty": "EASY",
      "tags": [
        "stack",
        "tree",
        "depth-first-search",
        "binary-tree"
      ],
      "classHeavy": false,
      "oracleTier": "bank",
      "oracleFnName": "preorderTraversal"
    },
    {
      "id": "0145",
      "slug": "binary-tree-postorder-traversal",
      "title": "Binary Tree Postorder Traversal",
      "difficulty": "EASY",
      "tags": [
        "stack",
        "tree",
        "depth-first-search",
        "binary-tree"
      ],
      "classHeavy": false,
      "oracleTier": "bank",
      "oracleFnName": "postorderTraversal"
    },
    {
      "id": "0146",
      "slug": "lru-cache",
      "title": "LRU Cache",
      "difficulty": "MEDIUM",
      "tags": [
        "hash-table",
        "linked-list",
        "design",
        "doubly-linked-list"
      ],
      "classHeavy": true,
      "oracleTier": "bank",
      "oracleFnName": "LRUCache"
    },
    {
      "id": "0147",
      "slug": "insertion-sort-list",
      "title": "Insertion Sort List",
      "difficulty": "MEDIUM",
      "tags": [
        "linked-list",
        "sorting"
      ],
      "classHeavy": false,
      "oracleTier": "bank",
      "oracleFnName": "insertionSortList"
    },
    {
      "id": "0148",
      "slug": "sort-list",
      "title": "Sort List",
      "difficulty": "MEDIUM",
      "tags": [
        "linked-list",
        "two-pointers",
        "divide-and-conquer",
        "sorting",
        "merge-sort"
      ],
      "classHeavy": false,
      "oracleTier": "bank",
      "oracleFnName": "sortList"
    },
    {
      "id": "0149",
      "slug": "max-points-on-a-line",
      "title": "Max Points on a Line",
      "difficulty": "HARD",
      "tags": [
        "array",
        "hash-table",
        "math",
        "geometry"
      ],
      "classHeavy": false,
      "oracleTier": "bank",
      "oracleFnName": "maxPoints"
    },
    {
      "id": "0150",
      "slug": "evaluate-reverse-polish-notation",
      "title": "Evaluate Reverse Polish Notation",
      "difficulty": "MEDIUM",
      "tags": [
        "array",
        "math",
        "stack"
      ],
      "classHeavy": false,
      "oracleTier": "bank",
      "oracleFnName": "evalRPN"
    },
    {
      "id": "0151",
      "slug": "reverse-words-in-a-string",
      "title": "Reverse Words in a String",
      "difficulty": "MEDIUM",
      "tags": [
        "two-pointers",
        "string"
      ],
      "classHeavy": false,
      "oracleTier": "bank",
      "oracleFnName": "reverseWords"
    },
    {
      "id": "0152",
      "slug": "maximum-product-subarray",
      "title": "Maximum Product Subarray",
      "difficulty": "MEDIUM",
      "tags": [
        "array",
        "dynamic-programming"
      ],
      "classHeavy": false,
      "oracleTier": "bank",
      "oracleFnName": "maxProduct"
    },
    {
      "id": "0153",
      "slug": "find-minimum-in-rotated-sorted-array",
      "title": "Find Minimum in Rotated Sorted Array",
      "difficulty": "MEDIUM",
      "tags": [
        "array",
        "binary-search"
      ],
      "classHeavy": false,
      "oracleTier": "bank",
      "oracleFnName": "findMin"
    },
    {
      "id": "0154",
      "slug": "find-minimum-in-rotated-sorted-array-ii",
      "title": "Find Minimum in Rotated Sorted Array II",
      "difficulty": "HARD",
      "tags": [
        "array",
        "binary-search"
      ],
      "classHeavy": false,
      "oracleTier": "bank",
      "oracleFnName": "findMin"
    },
    {
      "id": "0155",
      "slug": "min-stack",
      "title": "Min Stack",
      "difficulty": "MEDIUM",
      "tags": [
        "stack",
        "design"
      ],
      "classHeavy": true,
      "oracleTier": "bank",
      "oracleFnName": "MinStack"
    },
    {
      "id": "0156",
      "slug": "binary-tree-upside-down",
      "title": "Binary Tree Upside Down",
      "difficulty": "MEDIUM",
      "tags": [
        "tree",
        "depth-first-search",
        "binary-tree"
      ],
      "classHeavy": false,
      "oracleTier": "bank",
      "oracleFnName": "upsideDownBinaryTree"
    },
    {
      "id": "0157",
      "slug": "read-n-characters-given-read4",
      "title": "Read N Characters Given Read4",
      "difficulty": "EASY",
      "tags": [
        "array",
        "simulation",
        "interactive"
      ],
      "classHeavy": false,
      "oracleTier": "bank",
      "oracleFnName": "solution"
    },
    {
      "id": "0158",
      "slug": "read-n-characters-given-read4-ii-call-multiple-times",
      "title": "Read N Characters Given read4 II - Call Multiple Times",
      "difficulty": "HARD",
      "tags": [
        "array",
        "simulation",
        "interactive"
      ],
      "classHeavy": false,
      "oracleTier": "bank",
      "oracleFnName": "solution"
    },
    {
      "id": "0159",
      "slug": "longest-substring-with-at-most-two-distinct-characters",
      "title": "Longest Substring with At Most Two Distinct Characters",
      "difficulty": "MEDIUM",
      "tags": [
        "hash-table",
        "string",
        "sliding-window"
      ],
      "classHeavy": false,
      "oracleTier": "bank",
      "oracleFnName": "lengthOfLongestSubstringTwoDistinct"
    },
    {
      "id": "0160",
      "slug": "intersection-of-two-linked-lists",
      "title": "Intersection of Two Linked Lists",
      "difficulty": "EASY",
      "tags": [
        "hash-table",
        "linked-list",
        "two-pointers"
      ],
      "classHeavy": false,
      "oracleTier": "bank",
      "oracleFnName": "getIntersectionNode"
    }
  ]
}
