[
  {
    "file": "0428-serialize-and-deserialize-n-ary-tree.js",
    "reason": "no 'var fnName = function' pattern found"
  },
  {
    "file": "0431-encode-n-ary-tree-to-binary-tree.js",
    "reason": "no 'var fnName = function' pattern found"
  },
  {
    "file": "0675-cut-off-trees-for-golf-event.js",
    "reason": "no 'var fnName = function' pattern found"
  },
  {
    "file": "0679-24-game.js",
    "reason": "no 'var fnName = function' pattern found"
  },
  {
    "file": "0729-my-calendar-i.js",
    "reason": "no 'var fnName = function' pattern found"
  },
  {
    "file": "0732-my-calendar-iii.js",
    "reason": "no 'var fnName = function' pattern found"
  },
  {
    "file": "0761-special-binary-string.js",
    "reason": "no 'var fnName = function' pattern found"
  },
  {
    "file": "0764-largest-plus-sign.js",
    "reason": "no 'var fnName = function' pattern found"
  },
  {
    "file": "0765-couples-holding-hands.js",
    "reason": "no 'var fnName = function' pattern found"
  },
  {
    "file": "0766-toeplitz-matrix.js",
    "reason": "no 'var fnName = function' pattern found"
  },
  {
    "file": "1237-find-positive-integer-solution-for-a-given-equation.js",
    "reason": "no 'var fnName = function' pattern found"
  },
  {
    "file": "1239-maximum-length-of-a-concatenated-string-with-unique-characters.js",
    "reason": "no 'var fnName = function' pattern found"
  },
  {
    "file": "1240-tiling-a-rectangle-with-the-fewest-squares.js",
    "reason": "no 'var fnName = function' pattern found"
  },
  {
    "file": "1247-minimum-swaps-to-make-strings-equal.js",
    "reason": "no 'var fnName = function' pattern found"
  },
  {
    "file": "1293-shortest-path-in-a-grid-with-obstacles-elimination.js",
    "reason": "no 'var fnName = function' pattern found"
  },
  {
    "file": "1354-construct-target-array-with-multiple-sums.js",
    "reason": "no 'var fnName = function' pattern found"
  },
  {
    "file": "1359-count-all-valid-pickup-and-delivery-options.js",
    "reason": "no 'var fnName = function' pattern found"
  },
  {
    "file": "1362-closest-divisors.js",
    "reason": "no 'var fnName = function' pattern found"
  },
  {
    "file": "1416-restore-the-array.js",
    "reason": "no 'var fnName = function' pattern found"
  },
  {
    "file": "1420-build-array-where-you-can-find-the-maximum-exactly-k-comparisons.js",
    "reason": "no 'var fnName = function' pattern found"
  },
  {
    "file": "1534-count-good-triplets.js",
    "reason": "no 'var fnName = function' pattern found"
  },
  {
    "file": "1608-special-array-with-x-elements-greater-than-or-equal-x.js",
    "reason": "no 'var fnName = function' pattern found"
  },
  {
    "file": "2619-array-prototype-last.js",
    "reason": "no 'var fnName = function' pattern found"
  },
  {
    "file": "2621-sleep.js",
    "reason": "no 'var fnName = function' pattern found"
  },
  {
    "file": "2623-memoize.js",
    "reason": "no 'var fnName = function' pattern found"
  },
  {
    "file": "2624-snail-traversal.js",
    "reason": "no 'var fnName = function' pattern found"
  },
  {
    "file": "2630-memoize-ii.js",
    "reason": "no 'var fnName = function' pattern found"
  },
  {
    "file": "2631-group-by.js",
    "reason": "no 'var fnName = function' pattern found"
  },
  {
    "file": "2636-promise-pool.js",
    "reason": "no 'var fnName = function' pattern found"
  },
  {
    "file": "2693-call-function-with-custom-context.js",
    "reason": "no 'var fnName = function' pattern found"
  },
  {
    "file": "2694-event-emitter.js",
    "reason": "no 'var fnName = function' pattern found"
  },
  {
    "file": "2700-differences-between-two-objects.js",
    "reason": "no 'var fnName = function' pattern found"
  },
  {
    "file": "2723-add-two-promises.js",
    "reason": "no 'var fnName = function' pattern found"
  },
  {
    "file": "2726-calculator-with-method-chaining.js",
    "reason": "no 'var fnName = function' pattern found"
  },
  {
    "file": "2754-bind-function-to-context.js",
    "reason": "no 'var fnName = function' pattern found"
  },
  {
    "file": "2758-next-day.js",
    "reason": "no 'var fnName = function' pattern found"
  },
  {
    "file": "2774-array-upper-bound.js",
    "reason": "no 'var fnName = function' pattern found"
  },
  {
    "file": "2796-repeat-string.js",
    "reason": "no 'var fnName = function' pattern found"
  },
  {
    "file": "2803-factorial-generator.js",
    "reason": "no 'var fnName = function' pattern found"
  },
  {
    "file": "2804-array-prototype-foreach.js",
    "reason": "no 'var fnName = function' pattern found"
  },
  {
    "file": "2805-custom-interval.js",
    "reason": "no 'var fnName = function' pattern found"
  },
  {
    "file": "3272-find-the-count-of-good-integers.js",
    "reason": "no 'var fnName = function' pattern found"
  },
  {
    "file": "3306-count-of-substrings-containing-every-vowel-and-k-consonants-ii.js",
    "reason": "no 'var fnName = function' pattern found"
  }
]
